Workbook

Sheet Параметры
A1: Параметр | B1: Значение
A2: Заказов в месяц | B2: 20
A3: Средний чек | B3: 94000
A4: Средняя себестоимость | B4: 58000
A5: CAC (привлечение) | B5: 6500
A6: Фиксированные расходы (итого) | B6: =B27
A7: Инвестиции на старт | B7: 1200000
A9: Средний чек (из пакетов) | B9: =IF(Пакеты!B10=0,B3,Пакеты!B10)
A10: Себестоимость (из пакетов) | B10: =IF(Пакеты!B11=0,B4,Пакеты!B11)
A12: Доп. FIX на город (2-й/3-й) | B12: 250000
A13: Месяц запуска 2-го города (1-12) | B13: 5
A14: Месяц запуска 3-го города (1-12) | B14: 9
A15: Коэф. роста CAC (стресс) | B15: 1.3
A16: Коэф. падения чека (стресс) | B16: 0.8
A17: Коэф. доп. падения заказов зимой (стресс) | B17: 0.1
A18: FIX новой точки (редактируемо)
A19: 2 менеджера продаж | B19: 140000
A20: администратор/координатор | B20: 60000
A21: аренда шоурум+офис | B21: 70000
A22: коммуналка/связь/сервисы | B22: 15000
A23: хоз. расходы | B23: 8000
A24: транспорт | B24: 12000
A25: юр. и бухгалтерия | B25: 15000
A27: Итого FIX: ₽/мес | B27: =SUM(B19:B25)

Sheet Юнит-экономика
A1: Показатель | B1: Формула / Значение
A2: Валовая прибыль с заказа | B2: =Параметры!B9-Параметры!B10
A3: Вклад в покрытие | B3: =Параметры!B9-Параметры!B10-Параметры!B5
A4: Маржинальность, % | B4: =(Параметры!B9-Параметры!B10)/Параметры!B9

Sheet Продажи
A1: Показатель | B1: Значение
A2: Выручка | B2: =Параметры!B2*Параметры!B9
A3: Себестоимость | B3: =Параметры!B2*Параметры!B10
A4: Маркетинг | B4: =Параметры!B2*Параметры!B5
A5: Всего переменных | B5: =B3+B4

Sheet P&L
A1: Показатель | B1: Значение
A2: Выручка | B2: =Продажи!B2
A3: Переменные расходы | B3: =Продажи!B5
A4: Валовая прибыль | B4: =B2-B3
A5: Фиксированные расходы | B5: =Параметры!B6
A6: Чистая прибыль | B6: =B4-B5

Sheet Безубыточность
A1: Показатель | B1: Значение
A2: Точка безубыточности (заказов) | B2: =Параметры!B6/('Юнит-экономика'!B3)

Sheet Окупаемость
A1: Показатель | B1: Значение
A2: Срок окупаемости (мес) | B2: =IF('P&L'!B6<=0,"нет окупаемости",Параметры!B7/'P&L'!B6)
A3: Срок окупаемости (дней) | B3: =IF('P&L'!B6<=0,"нет окупаемости",(Параметры!B7/'P&L'!B6)*30)

Sheet Пакеты
A1: Пакет | B1: Цена | C1: Себестоимость | D1: Маржа | E1: Доля продаж
A2: Минимум | B2: 59900 | C2: 46000 | D2: =B2-C2 | E2: 0.1
A3: Стандарт | B3: 74900 | C3: 52000 | D3: =B3-C3 | E3: 0.15
A4: Стандарт+ | B4: 89900 | C4: 57000 | D4: =B4-C4 | E4: 0.35
A5: Семейный | B5: 99900 | C5: 60000 | D5: =B5-C5 | E5: 0.15
A6: Мемориал | B6: 114900 | C6: 64000 | D6: =B6-C6 | E6: 0.1
A7: Мемориал+ | B7: 129900 | C7: 68000 | D7: =B7-C7 | E7: 0.1
A8: Индивидуальный | B8: 159900 | C8: 90000 | D8: =B8-C8 | E8: 0.05
A10: Взвешенный средний чек | B10: =IF(SUM(E2:E8)=0,0,SUMPRODUCT(B2:B8,E2:E8)/SUM(E2:E8))
A11: Взвешенная себестоимость | B11: =IF(SUM(E2:E8)=0,0,SUMPRODUCT(C2:C8,E2:E8)/SUM(E2:E8))

Sheet KPI_Менеджеры
A1: Показатель | B1: План | C1: Факт | D1: Формула
A2: Лиды | B2: 120
A3: Договоры | B3: 30
A4: Конверсия | B4: 0.25 | D4: =IF(C2=0,0,C3/C2)
A5: Средний чек | B5: =Параметры!B9
A6: Выручка | D6: =C3*C5
A7: CAC | B7: =Параметры!B5

Sheet Сезонность
A1: Месяц | B1: Коэффициент | C1: Заказы (расчет)
A2: Январь | B2: 0 | C2: =Параметры!B2*B2
A3: Февраль | B3: 0 | C3: =Параметры!B2*B3
A4: Март | B4: 0.2 | C4: =Параметры!B2*B4
A5: Апрель | B5: 1 | C5: =Параметры!B2*B5
A6: Май | B6: 1 | C6: =Параметры!B2*B6
A7: Июнь | B7: 1.3 | C7: =Параметры!B2*B7
A8: Июль | B8: 0.8 | C8: =Параметры!B2*B8
A9: Август | B9: 1.1 | C9: =Параметры!B2*B9
A10: Сентябрь | B10: 1 | C10: =Параметры!B2*B10
A11: Октябрь | B11: 0.3 | C11: =Параметры!B2*B11
A12: Ноябрь | B12: 0.2 | C12: =Параметры!B2*B12
A13: Декабрь | B13: 0.1 | C13: =Параметры!B2*B13

Sheet CashFlow_12м
A1: Месяц | B1: Сезон. коэф. | C1: Заказы (1 город) | D1: Средний чек | E1: CAC | F1: Выручка | G1: Поступления 70% | H1: Поступления 30% (с прошлого мес) | I1: Всего поступлений | J1: COGS (себестоимость) | K1: Выплата COGS (70% + 30% прошл. мес) | L1: Маркетинг | M1: FIX | N1: Чистый ДДС месяца | O1: Накопленный ДДС
A2: Янв | B2: =Сезонность!B2 | C2: =Параметры!B2*B2 | D2: =Параметры!B9 | E2: =Параметры!B5 | F2: =C2*D2 | G2: =F2*0.7 | H2: 0 | I2: =G2+H2 | J2: =C2*Параметры!B10 | K2: =-J2*0.7 | L2: =-(C2*E2) | M2: =-Параметры!B6 | N2: =I2+K2+L2+M2 | O2: =N2
A3: Фев | B3: =Сезонность!B3 | C3: =Параметры!B2*B3 | D3: =Параметры!B9 | E3: =Параметры!B5 | F3: =C3*D3 | G3: =F3*0.7 | H3: =F2*0.3 | I3: =G3+H3 | J3: =C3*Параметры!B10 | K3: =-(J3*0.7 + J2*0.3) | L3: =-(C3*E3) | M3: =-Параметры!B6 | N3: =I3+K3+L3+M3 | O3: =O2+N3
A4: Мар | B4: =Сезонность!B4 | C4: =Параметры!B2*B4 | D4: =Параметры!B9 | E4: =Параметры!B5 | F4: =C4*D4 | G4: =F4*0.7 | H4: =F3*0.3 | I4: =G4+H4 | J4: =C4*Параметры!B10 | K4: =-(J4*0.7 + J3*0.3) | L4: =-(C4*E4) | M4: =-Параметры!B6 | N4: =I4+K4+L4+M4 | O4: =O3+N4
A5: Апр | B5: =Сезонность!B5 | C5: =Параметры!B2*B5 | D5: =Параметры!B9 | E5: =Параметры!B5 | F5: =C5*D5 | G5: =F5*0.7 | H5: =F4*0.3 | I5: =G5+H5 | J5: =C5*Параметры!B10 | K5: =-(J5*0.7 + J4*0.3) | L5: =-(C5*E5) | M5: =-Параметры!B6 | N5: =I5+K5+L5+M5 | O5: =O4+N5
A6: Май | B6: =Сезонность!B6 | C6: =Параметры!B2*B6 | D6: =Параметры!B9 | E6: =Параметры!B5 | F6: =C6*D6 | G6: =F6*0.7 | H6: =F5*0.3 | I6: =G6+H6 | J6: =C6*Параметры!B10 | K6: =-(J6*0.7 + J5*0.3) | L6: =-(C6*E6) | M6: =-Параметры!B6 | N6: =I6+K6+L6+M6 | O6: =O5+N6
A7: Июн | B7: =Сезонность!B7 | C7: =Параметры!B2*B7 | D7: =Параметры!B9 | E7: =Параметры!B5 | F7: =C7*D7 | G7: =F7*0.7 | H7: =F6*0.3 | I7: =G7+H7 | J7: =C7*Параметры!B10 | K7: =-(J7*0.7 + J6*0.3) | L7: =-(C7*E7) | M7: =-Параметры!B6 | N7: =I7+K7+L7+M7 | O7: =O6+N7
A8: Июл | B8: =Сезонность!B8 | C8: =Параметры!B2*B8 | D8: =Параметры!B9 | E8: =Параметры!B5 | F8: =C8*D8 | G8: =F8*0.7 | H8: =F7*0.3 | I8: =G8+H8 | J8: =C8*Параметры!B10 | K8: =-(J8*0.7 + J7*0.3) | L8: =-(C8*E8) | M8: =-Параметры!B6 | N8: =I8+K8+L8+M8 | O8: =O7+N8
A9: Авг | B9: =Сезонность!B9 | C9: =Параметры!B2*B9 | D9: =Параметры!B9 | E9: =Параметры!B5 | F9: =C9*D9 | G9: =F9*0.7 | H9: =F8*0.3 | I9: =G9+H9 | J9: =C9*Параметры!B10 | K9: =-(J9*0.7 + J8*0.3) | L9: =-(C9*E9) | M9: =-Параметры!B6 | N9: =I9+K9+L9+M9 | O9: =O8+N9
A10: Сен | B10: =Сезонность!B10 | C10: =Параметры!B2*B10 | D10: =Параметры!B9 | E10: =Параметры!B5 | F10: =C10*D10 | G10: =F10*0.7 | H10: =F9*0.3 | I10: =G10+H10 | J10: =C10*Параметры!B10 | K10: =-(J10*0.7 + J9*0.3) | L10: =-(C10*E10) | M10: =-Параметры!B6 | N10: =I10+K10+L10+M10 | O10: =O9+N10
A11: Окт | B11: =Сезонность!B11 | C11: =Параметры!B2*B11 | D11: =Параметры!B9 | E11: =Параметры!B5 | F11: =C11*D11 | G11: =F11*0.7 | H11: =F10*0.3 | I11: =G11+H11 | J11: =C11*Параметры!B10 | K11: =-(J11*0.7 + J10*0.3) | L11: =-(C11*E11) | M11: =-Параметры!B6 | N11: =I11+K11+L11+M11 | O11: =O10+N11
A12: Ноя | B12: =Сезонность!B12 | C12: =Параметры!B2*B12 | D12: =Параметры!B9 | E12: =Параметры!B5 | F12: =C12*D12 | G12: =F12*0.7 | H12: =F11*0.3 | I12: =G12+H12 | J12: =C12*Параметры!B10 | K12: =-(J12*0.7 + J11*0.3) | L12: =-(C12*E12) | M12: =-Параметры!B6 | N12: =I12+K12+L12+M12 | O12: =O11+N12
A13: Дек | B13: =Сезонность!B13 | C13: =Параметры!B2*B13 | D13: =Параметры!B9 | E13: =Параметры!B5 | F13: =C13*D13 | G13: =F13*0.7 | H13: =F12*0.3 | I13: =G13+H13 | J13: =C13*Параметры!B10 | K13: =-(J13*0.7 + J12*0.3) | L13: =-(C13*E13) | M13: =-Параметры!B6 | N13: =I13+K13+L13+M13 | O13: =O12+N13

Sheet Масштабирование
A1: Модель роста до 2–3 городов (заказы и прибыль по месяцам)
A3: Параметр | B3: Значение
A4: База заказов / мес (1 город) | B4: =Параметры!B2
A5: Доп. FIX на каждый новый город | B5: =Параметры!B12
A6: Запуск 2-го города (месяц) | B6: =Параметры!B13
A7: Запуск 3-го города (месяц) | B7: =Параметры!B14
A8: Средний чек (из пакетов) | B8: =Параметры!B9
A9: Себестоимость/заказ (из пакетов) | B9: =Параметры!B10
A10: CAC | B10: =Параметры!B5
A11: FIX (1 город) | B11: =Параметры!B6
A13: Месяц | B13: Коэф. сезонности | C13: Заказы (1 город) | D13: Заказы (2 города) | E13: Заказы (3 города) | F13: Прибыль (1 город) | G13: Прибыль (2 города) | H13: Прибыль (3 города)
A14: Янв | B14: =Сезонность!B2 | C14: =Параметры!B2*B14 | D14: =C14 + (Параметры!B2*B14)*IF($I14<$B$6,0,IF($I14=$B$6,0.5,IF($I14=$B$6+1,0.8,1))) | E14: =D14 + (Параметры!B2*B14)*IF($I14<$B$7,0,IF($I14=$B$7,0.5,IF($I14=$B$7+1,0.8,1))) | F14: =C14*(Параметры!B9-Параметры!B10-Параметры!B5) - Параметры!B6 | G14: =D14*(Параметры!B9-Параметры!B10-Параметры!B5) - (Параметры!B6 + Параметры!B12) | H14: =E14*(Параметры!B9-Параметры!B10-Параметры!B5) - (Параметры!B6 + 2*Параметры!B12) | I14: 1
A15: Фев | B15: =Сезонность!B3 | C15: =Параметры!B2*B15 | D15: =C15 + (Параметры!B2*B15)*IF($I15<$B$6,0,IF($I15=$B$6,0.5,IF($I15=$B$6+1,0.8,1))) | E15: =D15 + (Параметры!B2*B15)*IF($I15<$B$7,0,IF($I15=$B$7,0.5,IF($I15=$B$7+1,0.8,1))) | F15: =C15*(Параметры!B9-Параметры!B10-Параметры!B5) - Параметры!B6 | G15: =D15*(Параметры!B9-Параметры!B10-Параметры!B5) - (Параметры!B6 + Параметры!B12) | H15: =E15*(Параметры!B9-Параметры!B10-Параметры!B5) - (Параметры!B6 + 2*Параметры!B12) | I15: 2
A16: Мар | B16: =Сезонность!B4 | C16: =Параметры!B2*B16 | D16: =C16 + (Параметры!B2*B16)*IF($I16<$B$6,0,IF($I16=$B$6,0.5,IF($I16=$B$6+1,0.8,1))) | E16: =D16 + (Параметры!B2*B16)*IF($I16<$B$7,0,IF($I16=$B$7,0.5,IF($I16=$B$7+1,0.8,1))) | F16: =C16*(Параметры!B9-Параметры!B10-Параметры!B5) - Параметры!B6 | G16: =D16*(Параметры!B9-Параметры!B10-Параметры!B5) - (Параметры!B6 + Параметры!B12) | H16: =E16*(Параметры!B9-Параметры!B10-Параметры!B5) - (Параметры!B6 + 2*Параметры!B12) | I16: 3
A17: Апр | B17: =Сезонность!B5 | C17: =Параметры!B2*B17 | D17: =C17 + (Параметры!B2*B17)*IF($I17<$B$6,0,IF($I17=$B$6,0.5,IF($I17=$B$6+1,0.8,1))) | E17: =D17 + (Параметры!B2*B17)*IF($I17<$B$7,0,IF($I17=$B$7,0.5,IF($I17=$B$7+1,0.8,1))) | F17: =C17*(Параметры!B9-Параметры!B10-Параметры!B5) - Параметры!B6 | G17: =D17*(Параметры!B9-Параметры!B10-Параметры!B5) - (Параметры!B6 + Параметры!B12) | H17: =E17*(Параметры!B9-Параметры!B10-Параметры!B5) - (Параметры!B6 + 2*Параметры!B12) | I17: 4
A18: Май | B18: =Сезонность!B6 | C18: =Параметры!B2*B18 | D18: =C18 + (Параметры!B2*B18)*IF($I18<$B$6,0,IF($I18=$B$6,0.5,IF($I18=$B$6+1,0.8,1))) | E18: =D18 + (Параметры!B2*B18)*IF($I18<$B$7,0,IF($I18=$B$7,0.5,IF($I18=$B$7+1,0.8,1))) | F18: =C18*(Параметры!B9-Параметры!B10-Параметры!B5) - Параметры!B6 | G18: =D18*(Параметры!B9-Параметры!B10-Параметры!B5) - (Параметры!B6 + Параметры!B12) | H18: =E18*(Параметры!B9-Параметры!B10-Параметры!B5) - (Параметры!B6 + 2*Параметры!B12) | I18: 5
A19: Июн | B19: =Сезонность!B7 | C19: =Параметры!B2*B19 | D19: =C19 + (Параметры!B2*B19)*IF($I19<$B$6,0,IF($I19=$B$6,0.5,IF($I19=$B$6+1,0.8,1))) | E19: =D19 + (Параметры!B2*B19)*IF($I19<$B$7,0,IF($I19=$B$7,0.5,IF($I19=$B$7+1,0.8,1))) | F19: =C19*(Параметры!B9-Параметры!B10-Параметры!B5) - Параметры!B6 | G19: =D19*(Параметры!B9-Параметры!B10-Параметры!B5) - (Параметры!B6 + Параметры!B12) | H19: =E19*(Параметры!B9-Параметры!B10-Параметры!B5) - (Параметры!B6 + 2*Параметры!B12) | I19: 6
A20: Июл | B20: =Сезонность!B8 | C20: =Параметры!B2*B20 | D20: =C20 + (Параметры!B2*B20)*IF($I20<$B$6,0,IF($I20=$B$6,0.5,IF($I20=$B$6+1,0.8,1))) | E20: =D20 + (Параметры!B2*B20)*IF($I20<$B$7,0,IF($I20=$B$7,0.5,IF($I20=$B$7+1,0.8,1))) | F20: =C20*(Параметры!B9-Параметры!B10-Параметры!B5) - Параметры!B6 | G20: =D20*(Параметры!B9-Параметры!B10-Параметры!B5) - (Параметры!B6 + Параметры!B12) | H20: =E20*(Параметры!B9-Параметры!B10-Параметры!B5) - (Параметры!B6 + 2*Параметры!B12) | I20: 7
A21: Авг | B21: =Сезонность!B9 | C21: =Параметры!B2*B21 | D21: =C21 + (Параметры!B2*B21)*IF($I21<$B$6,0,IF($I21=$B$6,0.5,IF($I21=$B$6+1,0.8,1))) | E21: =D21 + (Параметры!B2*B21)*IF($I21<$B$7,0,IF($I21=$B$7,0.5,IF($I21=$B$7+1,0.8,1))) | F21: =C21*(Параметры!B9-Параметры!B10-Параметры!B5) - Параметры!B6 | G21: =D21*(Параметры!B9-Параметры!B10-Параметры!B5) - (Параметры!B6 + Параметры!B12) | H21: =E21*(Параметры!B9-Параметры!B10-Параметры!B5) - (Параметры!B6 + 2*Параметры!B12) | I21: 8
A22: Сен | B22: =Сезонность!B10 | C22: =Параметры!B2*B22 | D22: =C22 + (Параметры!B2*B22)*IF($I22<$B$6,0,IF($I22=$B$6,0.5,IF($I22=$B$6+1,0.8,1))) | E22: =D22 + (Параметры!B2*B22)*IF($I22<$B$7,0,IF($I22=$B$7,0.5,IF($I22=$B$7+1,0.8,1))) | F22: =C22*(Параметры!B9-Параметры!B10-Параметры!B5) - Параметры!B6 | G22: =D22*(Параметры!B9-Параметры!B10-Параметры!B5) - (Параметры!B6 + Параметры!B12) | H22: =E22*(Параметры!B9-Параметры!B10-Параметры!B5) - (Параметры!B6 + 2*Параметры!B12) | I22: 9
A23: Окт | B23: =Сезонность!B11 | C23: =Параметры!B2*B23 | D23: =C23 + (Параметры!B2*B23)*IF($I23<$B$6,0,IF($I23=$B$6,0.5,IF($I23=$B$6+1,0.8,1))) | E23: =D23 + (Параметры!B2*B23)*IF($I23<$B$7,0,IF($I23=$B$7,0.5,IF($I23=$B$7+1,0.8,1))) | F23: =C23*(Параметры!B9-Параметры!B10-Параметры!B5) - Параметры!B6 | G23: =D23*(Параметры!B9-Параметры!B10-Параметры!B5) - (Параметры!B6 + Параметры!B12) | H23: =E23*(Параметры!B9-Параметры!B10-Параметры!B5) - (Параметры!B6 + 2*Параметры!B12) | I23: 10
A24: Ноя | B24: =Сезонность!B12 | C24: =Параметры!B2*B24 | D24: =C24 + (Параметры!B2*B24)*IF($I24<$B$6,0,IF($I24=$B$6,0.5,IF($I24=$B$6+1,0.8,1))) | E24: =D24 + (Параметры!B2*B24)*IF($I24<$B$7,0,IF($I24=$B$7,0.5,IF($I24=$B$7+1,0.8,1))) | F24: =C24*(Параметры!B9-Параметры!B10-Параметры!B5) - Параметры!B6 | G24: =D24*(Параметры!B9-Параметры!B10-Параметры!B5) - (Параметры!B6 + Параметры!B12) | H24: =E24*(Параметры!B9-Параметры!B10-Параметры!B5) - (Параметры!B6 + 2*Параметры!B12) | I24: 11
A25: Дек | B25: =Сезонность!B13 | C25: =Параметры!B2*B25 | D25: =C25 + (Параметры!B2*B25)*IF($I25<$B$6,0,IF($I25=$B$6,0.5,IF($I25=$B$6+1,0.8,1))) | E25: =D25 + (Параметры!B2*B25)*IF($I25<$B$7,0,IF($I25=$B$7,0.5,IF($I25=$B$7+1,0.8,1))) | F25: =C25*(Параметры!B9-Параметры!B10-Параметры!B5) - Параметры!B6 | G25: =D25*(Параметры!B9-Параметры!B10-Параметры!B5) - (Параметры!B6 + Параметры!B12) | H25: =E25*(Параметры!B9-Параметры!B10-Параметры!B5) - (Параметры!B6 + 2*Параметры!B12) | I25: 12

Sheet Стресс_тест
A1: Стресс-тест: зима + рост CAC + падение чека (база vs стресс)
A3: Параметр | B3: База | C3: Стресс
A4: CAC множитель | B4: 1 | C4: =Параметры!B15
A5: Чек множитель | B5: 1 | C5: =Параметры!B16
A6: Зимние заказы множитель (Ноя–Фев) | B6: 1 | C6: =Параметры!B17
A8: Месяц | B8: Сезон. коэф. | C8: Заказы (база) | D8: Заказы (стресс) | E8: CAC (база) | F8: CAC (стресс) | G8: Чек (база) | H8: Чек (стресс) | I8: Прибыль (база) | J8: Прибыль (стресс) | K8: Δ прибыль
A9: Янв | B9: =Сезонность!B2 | C9: =Параметры!B2*B9 | D9: =C9*Параметры!B17 | E9: =Параметры!B5 | F9: =Параметры!B5*Параметры!B15 | G9: =Параметры!B9 | H9: =Параметры!B9*Параметры!B16 | I9: =C9*(G9-Параметры!B10-E9) - Параметры!B6 | J9: =D9*(H9-Параметры!B10-F9) - Параметры!B6 | K9: =J9-I9
A10: Фев | B10: =Сезонность!B3 | C10: =Параметры!B2*B10 | D10: =C10*Параметры!B17 | E10: =Параметры!B5 | F10: =Параметры!B5*Параметры!B15 | G10: =Параметры!B9 | H10: =Параметры!B9*Параметры!B16 | I10: =C10*(G10-Параметры!B10-E10) - Параметры!B6 | J10: =D10*(H10-Параметры!B10-F10) - Параметры!B6 | K10: =J10-I10
A11: Мар | B11: =Сезонность!B4 | C11: =Параметры!B2*B11 | D11: =C11 | E11: =Параметры!B5 | F11: =Параметры!B5*Параметры!B15 | G11: =Параметры!B9 | H11: =Параметры!B9*Параметры!B16 | I11: =C11*(G11-Параметры!B10-E11) - Параметры!B6 | J11: =D11*(H11-Параметры!B10-F11) - Параметры!B6 | K11: =J11-I11
A12: Апр | B12: =Сезонность!B5 | C12: =Параметры!B2*B12 | D12: =C12 | E12: =Параметры!B5 | F12: =Параметры!B5*Параметры!B15 | G12: =Параметры!B9 | H12: =Параметры!B9*Параметры!B16 | I12: =C12*(G12-Параметры!B10-E12) - Параметры!B6 | J12: =D12*(H12-Параметры!B10-F12) - Параметры!B6 | K12: =J12-I12
A13: Май | B13: =Сезонность!B6 | C13: =Параметры!B2*B13 | D13: =C13 | E13: =Параметры!B5 | F13: =Параметры!B5*Параметры!B15 | G13: =Параметры!B9 | H13: =Параметры!B9*Параметры!B16 | I13: =C13*(G13-Параметры!B10-E13) - Параметры!B6 | J13: =D13*(H13-Параметры!B10-F13) - Параметры!B6 | K13: =J13-I13
A14: Июн | B14: =Сезонность!B7 | C14: =Параметры!B2*B14 | D14: =C14 | E14: =Параметры!B5 | F14: =Параметры!B5*Параметры!B15 | G14: =Параметры!B9 | H14: =Параметры!B9*Параметры!B16 | I14: =C14*(G14-Параметры!B10-E14) - Параметры!B6 | J14: =D14*(H14-Параметры!B10-F14) - Параметры!B6 | K14: =J14-I14
A15: Июл | B15: =Сезонность!B8 | C15: =Параметры!B2*B15 | D15: =C15 | E15: =Параметры!B5 | F15: =Параметры!B5*Параметры!B15 | G15: =Параметры!B9 | H15: =Параметры!B9*Параметры!B16 | I15: =C15*(G15-Параметры!B10-E15) - Параметры!B6 | J15: =D15*(H15-Параметры!B10-F15) - Параметры!B6 | K15: =J15-I15
A16: Авг | B16: =Сезонность!B9 | C16: =Параметры!B2*B16 | D16: =C16 | E16: =Параметры!B5 | F16: =Параметры!B5*Параметры!B15 | G16: =Параметры!B9 | H16: =Параметры!B9*Параметры!B16 | I16: =C16*(G16-Параметры!B10-E16) - Параметры!B6 | J16: =D16*(H16-Параметры!B10-F16) - Параметры!B6 | K16: =J16-I16
A17: Сен | B17: =Сезонность!B10 | C17: =Параметры!B2*B17 | D17: =C17 | E17: =Параметры!B5 | F17: =Параметры!B5*Параметры!B15 | G17: =Параметры!B9 | H17: =Параметры!B9*Параметры!B16 | I17: =C17*(G17-Параметры!B10-E17) - Параметры!B6 | J17: =D17*(H17-Параметры!B10-F17) - Параметры!B6 | K17: =J17-I17
A18: Окт | B18: =Сезонность!B11 | C18: =Параметры!B2*B18 | D18: =C18 | E18: =Параметры!B5 | F18: =Параметры!B5*Параметры!B15 | G18: =Параметры!B9 | H18: =Параметры!B9*Параметры!B16 | I18: =C18*(G18-Параметры!B10-E18) - Параметры!B6 | J18: =D18*(H18-Параметры!B10-F18) - Параметры!B6 | K18: =J18-I18
A19: Ноя | B19: =Сезонность!B12 | C19: =Параметры!B2*B19 | D19: =C19*Параметры!B17 | E19: =Параметры!B5 | F19: =Параметры!B5*Параметры!B15 | G19: =Параметры!B9 | H19: =Параметры!B9*Параметры!B16 | I19: =C19*(G19-Параметры!B10-E19) - Параметры!B6 | J19: =D19*(H19-Параметры!B10-F19) - Параметры!B6 | K19: =J19-I19
A20: Дек | B20: =Сезонность!B13 | C20: =Параметры!B2*B20 | D20: =C20*Параметры!B17 | E20: =Параметры!B5 | F20: =Параметры!B5*Параметры!B15 | G20: =Параметры!B9 | H20: =Параметры!B9*Параметры!B16 | I20: =C20*(G20-Параметры!B10-E20) - Параметры!B6 | J20: =D20*(H20-Параметры!B10-F20) - Параметры!B6 | K20: =J20-I20
A21: ИТОГО за год | I21: =SUM(I9:I20) | J21: =SUM(J9:J20) | K21: =J21-I21
